jupytercontrib/__init__.py
jupytercontrib/mdoutputexporter.py
jupytercontrib/py2to3exporter.py
jupytercontrib/templates/md_output.tpl
jupytercontrib/tests/test_imports.py
jupytercontrib-0.0.7.dist-info/entry_points.txt
jupytercontrib-0.0.7.dist-info/LICENSE
jupytercontrib-0.0.7.dist-info/WHEEL
jupytercontrib-0.0.7.dist-info/METADATA
jupytercontrib-0.0.7.dist-info/RECORD
