Metadata-Version: 2.1
Name: jupytercontrib
Version: 0.0.7
Summary: Some Jupyter contrib extensions
Home-page: https://github.com/Carreau/jupytercontrib
License: UNKNOWN
Author: Matthias Bussonnier
Author-email: bussonniermatthias@gmail.com
Classifier: License :: OSI Approved :: MIT License
Requires-Dist: nbconvert
